hybmkg_pycast/__init__.py
hybmkg_pycast/hybmkg_pycast.yaml
hybmkg_pycast/config/__init__.py
hybmkg_pycast/config/dl_default.json
hybmkg_pycast/config/ml_default.json
hybmkg_pycast/config/ml_tuned.json
hybmkg_pycast/config/stats_default.json
hybmkg_pycast/config/stats_tuned.json
hybmkg_pycast/data/__init__.py
hybmkg_pycast/data/data_enso.csv
hybmkg_pycast/data/mswep_bali_1979_2024.nc
hybmkg_pycast/model/__init__.py
hybmkg_pycast/model/dl.py
hybmkg_pycast/model/ml.py
hybmkg_pycast/model/overgrid.py
hybmkg_pycast/model/overgrid_parallel.py
hybmkg_pycast/model/stats.py
hybmkg_pycast-0.1.5.dist-info/METADATA
hybmkg_pycast-0.1.5.dist-info/WHEEL
hybmkg_pycast-0.1.5.dist-info/top_level.txt
hybmkg_pycast-0.1.5.dist-info/RECORD
