Metadata-Version: 2.4
Name: hybmkg-pycast
Version: 0.1.5
Summary: Hybrid climate forecasting framework for BMKG using Python
Author-email: Nurdeka Hidayanto <nurdeka.bmkg@gmail.com>
License: MIT
Project-URL: Source, https://github.com/nurdeka/hybmkg_pycast
Requires-Python: >=3.10
Requires-Dist: numpy>=1.26.0
Requires-Dist: pandas>=2.3.0
Requires-Dist: scipy>=1.15.0
Requires-Dist: matplotlib>=3.10.0
Requires-Dist: xarray>=2025.6.0
Requires-Dist: netCDF4>=1.7.0
Requires-Dist: cartopy>=0.25.0
Requires-Dist: pyproj>=3.7.0
Requires-Dist: shapely>=2.0.0
Requires-Dist: joblib>=1.3.0
Requires-Dist: tqdm>=4.67.0
Requires-Dist: simpful>=2.12.0
Requires-Dist: scikit-learn>=1.7.0
Requires-Dist: xgboost>=3.1.0
Requires-Dist: lightgbm>=4.6.0
Requires-Dist: tensorflow>=2.15.0
Requires-Dist: keras>=2.15.0
Requires-Dist: statsmodels>=0.14.0
Requires-Dist: pmdarima>=2.0.0
Requires-Dist: PyWavelets>=1.6.0
